pycryptlib/__init__.py
pycryptlib-1.1.5.dist-info/METADATA
pycryptlib-1.1.5.dist-info/WHEEL
pycryptlib-1.1.5.dist-info/top_level.txt
pycryptlib-1.1.5.dist-info/RECORD
