Metadata-Version: 2.1
Name: pycryptlib
Version: 1.1.5
Summary: Package that helps with cryptography
Home-page: UNKNOWN
Author: NHJonas
Author-email: nick.faltermeier@gmx.de
License: UNKNOWN
Keywords: python
Platform: UNKNOWN
Classifier: Operating System :: Microsoft :: Windows
